{
  "version": "7",
  "dialect": "postgresql",
  "entries": [
    {
      "idx": 0,
      "version": "7",
      "when": 1770921278747,
      "tag": "0000_amusing_domino",
      "breakpoints": true
    },
    {
      "idx": 1,
      "version": "7",
      "when": 1770933056962,
      "tag": "0001_free_wonder_man",
      "breakpoints": true
    },
    {
      "idx": 2,
      "version": "7",
      "when": 1770992652142,
      "tag": "0002_yummy_wallop",
      "breakpoints": true
    },
    {
      "idx": 3,
      "version": "7",
      "when": 1771359638004,
      "tag": "0003_absent_retro_girl",
      "breakpoints": true
    },
    {
      "idx": 4,
      "version": "7",
      "when": 1771525119134,
      "tag": "0004_material_mattie_franklin",
      "breakpoints": true
    },
    {
      "idx": 5,
      "version": "7",
      "when": 1771548130846,
      "tag": "0005_amused_drax",
      "breakpoints": true
    },
    {
      "idx": 6,
      "version": "7",
      "when": 1771615719268,
      "tag": "0006_messy_garia",
      "breakpoints": true
    },
    {
      "idx": 7,
      "version": "7",
      "when": 1772208121967,
      "tag": "0007_brief_domino",
      "breakpoints": true
    }
  ]
}